kcidb_io/__init__.py
kcidb_io/misc.py
kcidb_io/test_misc.py
kcidb_io/schema/__init__.py
kcidb_io/schema/abstract.py
kcidb_io/schema/test_abstract.py
kcidb_io/schema/test_v03_00.py
kcidb_io/schema/test_v04_00.py
kcidb_io/schema/test_v04_03.py
kcidb_io/schema/test_v05_00.py
kcidb_io/schema/v01_01.py
kcidb_io/schema/v02_00.py
kcidb_io/schema/v03_00.py
kcidb_io/schema/v04_00.py
kcidb_io/schema/v04_01.py
kcidb_io/schema/v04_02.py
kcidb_io/schema/v04_03.py
kcidb_io/schema/v04_04.py
kcidb_io/schema/v04_05.py
kcidb_io/schema/v05_00.py
kcidb_io/schema/v05_01.py
kcidb_io/schema/v05_02.py
kcidb_io/schema/v05_03.py
kcidb_io/schema/v1.py
kcidb_io/schema/v2.py
kcidb_io/schema/v3.py
kcidb_io/schema/v4.py
kcidb_io-140.dist-info/licenses/LICENSE
kcidb_io-140.dist-info/METADATA
kcidb_io-140.dist-info/WHEEL
kcidb_io-140.dist-info/top_level.txt
kcidb_io-140.dist-info/RECORD
