Metadata-Version: 2.4
Name: kcidb-io
Version: 140
Summary: KCIDB = Linux Kernel CI reporting - I/O data library
Author-email: "kernelci.org" <kernelci@lists.linux.dev>
License-Expression: GPL-2.0-or-later
Project-URL: Homepage, https://github.com/kernelci/kcidb-io
Classifier: Development Status :: 5 - Production/Stable
Classifier: Intended Audience :: Developers
Classifier: Operating System :: OS Independent
Classifier: Programming Language :: Python :: 3.10
Classifier: Topic :: Software Development :: Libraries
Requires-Python: >=3.10
License-File: LICENSE
Requires-Dist: jsonschema[format]
Provides-Extra: dev
Requires-Dist: flake8; extra == "dev"
Requires-Dist: pylint; extra == "dev"
Requires-Dist: pytest; extra == "dev"
Dynamic: license-file
